<?xml version="1.0" encoding="UTF-8"?>
<rindja-generic-suggestor version="1.0">
    <developer>
        <name>kevin.qian</name>
    </developer>

    <description>
        盘点任务行查询建议器
    </description>

    <maxRows>20</maxRows>

    <statement>
        <table name="ivline"/>
        <param column="cmpnid" type="=" expr="_companyId"/>
        <param column="ivlnid" type="=" expr="fieldValue"/>
        <param column="XXX" expr="searchValue"/>
        <param condition="or" column="XXX" expr="searchValue"/>
        <order by="XXX desc"/>
    </statement>

    <fields>
        <field name="value" expr="XXX"/>
        <field name="label" expr="XXX"/>
    </fields>
</rindja-generic-suggestor>
